constancy/__init__.py
constancy/core.py
constancy-0.2.0.dist-info/LICENSE
constancy-0.2.0.dist-info/METADATA
constancy-0.2.0.dist-info/WHEEL
constancy-0.2.0.dist-info/top_level.txt
constancy-0.2.0.dist-info/RECORD
