Metadata-Version: 2.1
Name: constancy
Version: 0.2.0
Summary: Container for constants.
Author-email: Ilia Lazarev <the.ilia.lazarev@gmail.com>
Project-URL: Homepage, https://github.com/kephircheek/python-constancy
License-File: LICENSE
Provides-Extra: dev
Requires-Dist: isort[colors] (==5.11.4) ; extra == 'dev'
Requires-Dist: black (==22.12.0) ; extra == 'dev'
